mbed_project/__init__.py
mbed_project/_version.py
mbed_project/exceptions.py
mbed_project/mbed_program.py
mbed_project/mbed_project.py
mbed_project/_internal/__init__.py
mbed_project/_internal/git_utils.py
mbed_project/_internal/libraries.py
mbed_project/_internal/progress.py
mbed_project/_internal/project_data.py
mbed_project/mbed_tools/__init__.py
mbed_project/mbed_tools/cli.py
mbed_project-2.0.1.dist-info/LICENSE
mbed_project-2.0.1.dist-info/METADATA
mbed_project-2.0.1.dist-info/WHEEL
mbed_project-2.0.1.dist-info/top_level.txt
mbed_project-2.0.1.dist-info/RECORD
