Metadata-Version: 2.1
Name: mbed-project
Version: 2.0.1
Summary: Project and library management for Mbed OS
Home-page: https://github.com/ARMmbed/mbed-project
Author: Mbed team
Author-email: support@mbed.com
License: Apache 2.0
Keywords: Arm Mbed OS MbedOS project library
Platform: UNKNOWN
Classifier: Development Status :: 3 - Alpha
Classifier: Intended Audience :: Developers
Classifier: License :: OSI Approved :: Apache Software License
Classifier: Programming Language :: Python
Classifier: Programming Language :: Python :: 3 :: Only
Classifier: Programming Language :: Python :: 3.6
Classifier: Programming Language :: Python :: 3.7
Classifier: Programming Language :: Python :: 3.8
Classifier: Topic :: Software Development :: Build Tools
Classifier: Topic :: Software Development :: Embedded Systems
Requires-Python: >=3.6,<4
Requires-Dist: python-dotenv
Requires-Dist: Click (==7.0)
Requires-Dist: tabulate
Requires-Dist: mbed-tools-lib (~=1.2)
Requires-Dist: GitPython
Requires-Dist: tqdm
Requires-Dist: dataclasses ; python_version < "3.7"
